pyjoy/__init__.py
pyjoy/__main__.py
pyjoy/backends/__init__.py
pyjoy/backends/c/__init__.py
pyjoy/backends/c/builder.py
pyjoy/backends/c/converter.py
pyjoy/backends/c/emitter.py
pyjoy/backends/c/preprocessor.py
pyjoy/backends/c/runtime/joy_primitives.c
pyjoy/backends/c/runtime/joy_runtime.c
pyjoy/backends/c/runtime/joy_runtime.h
pyjoy/errors.py
pyjoy/evaluator/__init__.py
pyjoy/evaluator/aggregate.py
pyjoy/evaluator/arithmetic.py
pyjoy/evaluator/combinators.py
pyjoy/evaluator/core.py
pyjoy/evaluator/io.py
pyjoy/evaluator/logic.py
pyjoy/evaluator/stack_ops.py
pyjoy/evaluator/system.py
pyjoy/evaluator/types.py
pyjoy/parser.py
pyjoy/primitives.py
pyjoy/py.typed
pyjoy/repl.py
pyjoy/scanner.py
pyjoy/stack.py
pyjoy/stdlib/agglib.joy
pyjoy/stdlib/fraclib.joy
pyjoy/stdlib/grmlib.joy
pyjoy/stdlib/inilib.joy
pyjoy/stdlib/lazlib.joy
pyjoy/stdlib/lsplib.joy
pyjoy/stdlib/mthlib.joy
pyjoy/stdlib/mtrlib.joy
pyjoy/stdlib/numlib.joy
pyjoy/stdlib/plglib.joy
pyjoy/stdlib/prelib.joy
pyjoy/stdlib/replib.joy
pyjoy/stdlib/seqlib.joy
pyjoy/stdlib/symlib.joy
pyjoy/stdlib/tutlib.joy
pyjoy/stdlib/typlib.joy
pyjoy/stdlib/usrlib.joy
pyjoy/types.py
pyjoy_lang-0.1.2.dist-info/licenses/LICENSE
pyjoy_lang-0.1.2.dist-info/WHEEL
pyjoy_lang-0.1.2.dist-info/entry_points.txt
pyjoy_lang-0.1.2.dist-info/METADATA
pyjoy_lang-0.1.2.dist-info/RECORD
