Metadata-Version: 2.4
Name: pyjoy-lang
Version: 0.1.2
Summary: A Python implementation of the Joy programming language with C code generation
Keywords: joy,concatenative,stack-based,functional,programming-language,interpreter,compiler,c-code-generation
Author: Shakeeb Alireza
Author-email: Shakeeb Alireza <shakfu@users.noreply.github.com>
License-Expression: GPL-3.0-or-later
License-File: LICENSE
Classifier: Development Status :: 4 - Beta
Classifier: Environment :: Console
Classifier: Intended Audience :: Developers
Classifier: Intended Audience :: Education
Classifier: Intended Audience :: Science/Research
Classifier: License :: OSI Approved :: GNU General Public License v3 or later (GPLv3+)
Classifier: Operating System :: OS Independent
Classifier: Programming Language :: C
Classifier: Programming Language :: Python :: 3
Classifier: Programming Language :: Python :: 3.13
Classifier: Programming Language :: Python :: Implementation :: CPython
Classifier: Topic :: Software Development :: Compilers
Classifier: Topic :: Software Development :: Interpreters
Classifier: Typing :: Typed
Maintainer: Shakeeb Alireza
Maintainer-email: Shakeeb Alireza <shakfu@users.noreply.github.com>
Requires-Python: >=3.13
Project-URL: Changelog, https://github.com/shakfu/pyjoy-lang/blob/main/CHANGELOG.md
Project-URL: Documentation, https://github.com/shakfu/pyjoy-lang#readme
Project-URL: Homepage, https://github.com/shakfu/pyjoy-lang
Project-URL: Issues, https://github.com/shakfu/pyjoy-lang/issues
Project-URL: Repository, https://github.com/shakfu/pyjoy-lang.git
